bioamla/__init__.py
bioamla/_internal/templates/__init__.py
bioamla/adapters/__init__.py
bioamla/adapters/opensoundscape/__init__.py
bioamla/adapters/opensoundscape/audio.py
bioamla/adapters/opensoundscape/cnn.py
bioamla/adapters/opensoundscape/models.py
bioamla/adapters/opensoundscape/preprocessing.py
bioamla/adapters/opensoundscape/ribbit.py
bioamla/adapters/opensoundscape/spectrogram.py
bioamla/adapters/pydub/__init__.py
bioamla/adapters/pydub/audio.py
bioamla/cli/__init__.py
bioamla/cli/batch_options.py
bioamla/cli/cli.py
bioamla/cli/factory.py
bioamla/cli/progress.py
bioamla/cli/service_helpers.py
bioamla/cli/commands/__init__.py
bioamla/cli/commands/annotation.py
bioamla/cli/commands/audio.py
bioamla/cli/commands/batch.py
bioamla/cli/commands/catalogs.py
bioamla/cli/commands/cluster.py
bioamla/cli/commands/config.py
bioamla/cli/commands/dataset.py
bioamla/cli/commands/detect.py
bioamla/cli/commands/indices.py
bioamla/cli/commands/models.py
bioamla/core/annotations.py
bioamla/core/ast.py
bioamla/core/ast_model.py
bioamla/core/audio.py
bioamla/core/base.py
bioamla/core/birdnet.py
bioamla/core/client.py
bioamla/core/clustering.py
bioamla/core/config.py
bioamla/core/constants.py
bioamla/core/detectors.py
bioamla/core/device.py
bioamla/core/files.py
bioamla/core/indices.py
bioamla/core/inference.py
bioamla/core/metadata.py
bioamla/core/ml.py
bioamla/core/signal.py
bioamla/core/torchaudio.py
bioamla/core/utils.py
bioamla/core/visualize.py
bioamla/dev/__init__.py
bioamla/dev/active_learning.py
bioamla/dev/datasets.py
bioamla/dev/diagnostics.py
bioamla/dev/discovery.py
bioamla/dev/downloads.py
bioamla/dev/evaluate.py
bioamla/dev/explore.py
bioamla/dev/io.py
bioamla/dev/realtime.py
bioamla/dev/responses.py
bioamla/dev/training.py
bioamla/models/__init__.py
bioamla/models/annotation.py
bioamla/models/ast.py
bioamla/models/audio.py
bioamla/models/base.py
bioamla/models/batch.py
bioamla/models/birdnet.py
bioamla/models/clustering.py
bioamla/models/cnn.py
bioamla-0.1.8.dist-info/METADATA
bioamla-0.1.8.dist-info/WHEEL
bioamla-0.1.8.dist-info/entry_points.txt
bioamla-0.1.8.dist-info/licenses/LICENSE
bioamla-0.1.8.dist-info/RECORD
