Metadata-Version: 2.4
Name: bioamla
Version: 0.1.8
Summary: Bioacoustics & Machine Learning Applications
Project-URL: Homepage, https://github.com/jmcmeen/bioamla
Author-email: John McMeen <johnmcmeen@gmail.com>
License-File: LICENSE
Classifier: Operating System :: OS Independent
Classifier: Programming Language :: Python :: 3
Requires-Python: >=3.8
Requires-Dist: ai-edge-litert>=1.0.0
Requires-Dist: audiomentations
Requires-Dist: bioacoustics-model-zoo>=0.8.0
Requires-Dist: click
Requires-Dist: datasets[audio]
Requires-Dist: evaluate
Requires-Dist: hdbscan>=0.8.0
Requires-Dist: librosa
Requires-Dist: matplotlib
Requires-Dist: onnx>=1.14.0
Requires-Dist: opensoundscape>=0.12.0
Requires-Dist: pydantic>=2.0
Requires-Dist: pydub
Requires-Dist: pyinaturalist
Requires-Dist: requests>=2.28.0
Requires-Dist: rich
Requires-Dist: scikit-learn>=1.0.0
Requires-Dist: scipy
Requires-Dist: sounddevice>=0.4.0
Requires-Dist: soundfile
Requires-Dist: tensorflow>=2.15.0
Requires-Dist: textual
Requires-Dist: tf-keras>=2.15.0
Requires-Dist: timm>=1.0.0
Requires-Dist: tomli>=2.0; python_version < '3.11'
Requires-Dist: torch
Requires-Dist: torchaudio
Requires-Dist: torchvision
Requires-Dist: transformers[torch]
Requires-Dist: umap-learn>=0.5.0
Provides-Extra: all
Requires-Dist: build; extra == 'all'
Requires-Dist: mlflow>=2.0; extra == 'all'
Requires-Dist: pytest-asyncio; extra == 'all'
Requires-Dist: pytest-benchmark>=4.0; extra == 'all'
Requires-Dist: pytest-cov; extra == 'all'
Requires-Dist: pytest-mock; extra == 'all'
Requires-Dist: pytest>=7.0; extra == 'all'
Requires-Dist: ruff; extra == 'all'
Requires-Dist: sphinx>=7.0; extra == 'all'
Requires-Dist: twine; extra == 'all'
Provides-Extra: dev
Requires-Dist: build; extra == 'dev'
Requires-Dist: pytest-asyncio; extra == 'dev'
Requires-Dist: pytest-benchmark>=4.0; extra == 'dev'
Requires-Dist: pytest-cov; extra == 'dev'
Requires-Dist: pytest-mock; extra == 'dev'
Requires-Dist: pytest>=7.0; extra == 'dev'
Requires-Dist: ruff; extra == 'dev'
Requires-Dist: twine; extra == 'dev'
Provides-Extra: docs
Requires-Dist: sphinx>=7.0; extra == 'docs'
Provides-Extra: mlflow
Requires-Dist: mlflow>=2.0; extra == 'mlflow'
